{"lastUsed":1659430894375,"path":"C:\/LSH\/workspace","projectCount":9,"recentFiles":[{"path":"\/banking\/src\/main\/webapp\/WEB-INF\/views\/account","parentWorkspace":"C:\/LSH\/workspace","name":"withdraw.jsp","lastModified":1659422924943,"locationURI":"file:\/C:\/LSH\/workspace\/banking\/src\/main\/webapp\/WEB-INF\/views\/account\/withdraw.jsp"},{"path":"\/banking\/src\/main\/java\/com\/varxyz\/banking\/mvc\/controller","parentWorkspace":"C:\/LSH\/workspace","name":"BankingController.java","lastModified":1659430264241,"locationURI":"file:\/C:\/LSH\/workspace\/banking\/src\/main\/java\/com\/varxyz\/banking\/mvc\/controller\/BankingController.java"},{"path":"\/banking\/src\/main\/java\/com\/varxyz\/banking\/mvc\/dto","parentWorkspace":"C:\/LSH\/workspace","name":"Customer.java","lastModified":1659399782237,"locationURI":"file:\/C:\/LSH\/workspace\/banking\/src\/main\/java\/com\/varxyz\/banking\/mvc\/dto\/Customer.java"},{"path":"\/banking\/src\/main\/java\/com\/varxyz\/banking\/mvc\/dto","parentWorkspace":"C:\/LSH\/workspace","name":"Account.java","lastModified":1659422758353,"locationURI":"file:\/C:\/LSH\/workspace\/banking\/src\/main\/java\/com\/varxyz\/banking\/mvc\/dto\/Account.java"},{"path":"\/banking\/src\/main\/java\/com\/varxyz\/banking\/jdbc","parentWorkspace":"C:\/LSH\/workspace","name":"banking.sql","lastModified":1659424452048,"locationURI":"file:\/C:\/LSH\/workspace\/banking\/src\/main\/java\/com\/varxyz\/banking\/jdbc\/banking.sql"},{"path":"\/banking","parentWorkspace":"C:\/LSH\/workspace","name":"pom.xml","lastModified":1659399781656,"locationURI":"file:\/C:\/LSH\/workspace\/banking\/pom.xml"},{"path":"\/jvx330","parentWorkspace":"C:\/LSH\/workspace","name":"pom.xml","lastModified":1659399781656,"locationURI":"file:\/C:\/LSH\/workspace\/jvx330\/pom.xml"},{"path":"\/banking\/src\/main\/java\/com\/varxyz\/banking\/mvc\/dao","parentWorkspace":"C:\/LSH\/workspace","name":"LoginDao.java","lastModified":1659405331991,"locationURI":"file:\/C:\/LSH\/workspace\/banking\/src\/main\/java\/com\/varxyz\/banking\/mvc\/dao\/LoginDao.java"},{"path":"\/banking\/src\/main\/java\/com\/varxyz\/banking\/mvc\/dao","parentWorkspace":"C:\/LSH\/workspace","name":"AccountDao.java","lastModified":1659427098470,"locationURI":"file:\/C:\/LSH\/workspace\/banking\/src\/main\/java\/com\/varxyz\/banking\/mvc\/dao\/AccountDao.java"},{"path":"\/banking\/src\/main\/java\/com\/varxyz\/banking\/service","parentWorkspace":"C:\/LSH\/workspace","name":"AccountService.java","lastModified":1659422833128,"locationURI":"file:\/C:\/LSH\/workspace\/banking\/src\/main\/java\/com\/varxyz\/banking\/service\/AccountService.java"},{"path":"\/jvx330\/src\/main\/webapp\/WEB-INF","parentWorkspace":"C:\/LSH\/workspace","name":"web.xml","lastModified":1659409981347,"locationURI":"file:\/C:\/LSH\/workspace\/jvx330\/src\/main\/webapp\/WEB-INF\/web.xml"},{"path":"\/banking\/src\/main\/webapp\/WEB-INF","parentWorkspace":"C:\/LSH\/workspace","name":"web.xml","lastModified":1659404121699,"locationURI":"file:\/C:\/LSH\/workspace\/banking\/src\/main\/webapp\/WEB-INF\/web.xml"},{"path":"\/banking\/src\/main\/webapp\/WEB-INF\/views\/account","parentWorkspace":"C:\/LSH\/workspace","name":"deposit.jsp","lastModified":1659430229900,"locationURI":"file:\/C:\/LSH\/workspace\/banking\/src\/main\/webapp\/WEB-INF\/views\/account\/deposit.jsp"},{"path":"\/banking\/src\/main\/java\/com\/varxyz\/banking\/service","parentWorkspace":"C:\/LSH\/workspace","name":"AccountServiceImpl.java","lastModified":1659425440868,"locationURI":"file:\/C:\/LSH\/workspace\/banking\/src\/main\/java\/com\/varxyz\/banking\/service\/AccountServiceImpl.java"},{"path":"\/banking\/src\/main\/java\/com\/varxyz\/banking\/service","parentWorkspace":"C:\/LSH\/workspace","name":"LoginService.java","lastModified":1659405457493,"locationURI":"file:\/C:\/LSH\/workspace\/banking\/src\/main\/java\/com\/varxyz\/banking\/service\/LoginService.java"},{"path":"\/banking\/src\/main\/java\/com\/varxyz\/banking\/service","parentWorkspace":"C:\/LSH\/workspace","name":"LoginServiceImpl.java","lastModified":1659399781656,"locationURI":"file:\/C:\/LSH\/workspace\/banking\/src\/main\/java\/com\/varxyz\/banking\/service\/LoginServiceImpl.java"},{"path":"\/banking\/src\/main\/webapp\/WEB-INF\/views\/account","parentWorkspace":"C:\/LSH\/workspace","name":"successFindAccount.jsp","lastModified":1659425285625,"locationURI":"file:\/C:\/LSH\/workspace\/banking\/src\/main\/webapp\/WEB-INF\/views\/account\/successFindAccount.jsp"}]}